cappy/__init__.py
cappy/__main__.py
cappy/config.ini
cappy/configgen.py
cappy/utils.py
cappy/fonts/fut.ttf
cappy_cli-1.1.7.dist-info/LICENSE
cappy_cli-1.1.7.dist-info/METADATA
cappy_cli-1.1.7.dist-info/WHEEL
cappy_cli-1.1.7.dist-info/dependency_links.txt
cappy_cli-1.1.7.dist-info/entry_points.txt
cappy_cli-1.1.7.dist-info/top_level.txt
cappy_cli-1.1.7.dist-info/RECORD
