Metadata-Version: 2.1
Name: cappy-cli
Version: 1.1.7
Summary: A cli tool to add captions to images.
Home-page: https://github.com/asheeeshh/cappy
Author: ashish
Author-email: asheeshh@duck.com
License: MIT
Platform: UNKNOWN
Classifier: License :: OSI Approved :: MIT License
Classifier: Programming Language :: Python :: 3.8
Classifier: Programming Language :: Python :: 3.9
Classifier: Programming Language :: Python :: 3.10
License-File: LICENSE
Requires-Dist: click (==8.1.2)
Requires-Dist: halo (==0.0.31)
Requires-Dist: imgurpython (==1.1.7)
Requires-Dist: Pillow (==9.1.1)
Requires-Dist: python-dotenv (==0.20.0)
Requires-Dist: requests (==2.27.1)
